muradian/__init__.py
muradian/msc.py
muradian_strCalc-0.0.6.dist-info/LICENSE.txt
muradian_strCalc-0.0.6.dist-info/METADATA
muradian_strCalc-0.0.6.dist-info/WHEEL
muradian_strCalc-0.0.6.dist-info/top_level.txt
muradian_strCalc-0.0.6.dist-info/RECORD
