Metadata-Version: 2.1
Name: muradian-strCalc
Version: 0.0.6
Summary: A best usefull Function for assistant or text to speech services
Author: Mozadded Alfeshani
Author-email: developer.mozadded@gmail.com
Keywords: python,calcutor,assistant,string calculator
Classifier: Development Status :: 1 - Planning
Classifier: Intended Audience :: Developers
Classifier: Programming Language :: Python :: 3
Classifier: Operating System :: Unix
Classifier: Operating System :: MacOS :: MacOS X
Classifier: Operating System :: Microsoft :: Windows
License-File: LICENSE.txt
